wasapaso/__init__.py
wasapaso/_http_client.py
wasapaso/client.py
wasapaso/exceptions.py
wasapaso/py.typed
wasapaso/models/__init__.py
wasapaso/models/api_key.py
wasapaso/models/message.py
wasapaso/models/session.py
wasapaso/resources/__init__.py
wasapaso/resources/base.py
wasapaso/resources/messages.py
wasapaso/resources/sessions.py
wasapaso-0.1.1.dist-info/licenses/LICENSE
wasapaso-0.1.1.dist-info/METADATA
wasapaso-0.1.1.dist-info/WHEEL
wasapaso-0.1.1.dist-info/top_level.txt
wasapaso-0.1.1.dist-info/RECORD
