Metadata-Version: 2.4
Name: wasapaso
Version: 0.1.1
Summary: SDK de Python oficial para la API de Wasapaso - Gestión de WhatsApp
Author-email: Wasapaso Team <support@wasapaso.com>
License: MIT
Project-URL: Homepage, https://wasapaso.com
Project-URL: Documentation, https://docs.wasapaso.com/sdk/python
Project-URL: Repository, https://github.com/victalejo/wasapaso-python-sdk
Project-URL: Issues, https://github.com/victalejo/wasapaso-python-sdk/issues
Keywords: whatsapp,api,messaging,wasapaso,async
Classifier: Development Status :: 4 - Beta
Classifier: Intended Audience :: Developers
Classifier: License :: OSI Approved :: MIT License
Classifier: Operating System :: OS Independent
Classifier: Programming Language :: Python :: 3
Classifier: Programming Language :: Python :: 3.8
Classifier: Programming Language :: Python :: 3.9
Classifier: Programming Language :: Python :: 3.10
Classifier: Programming Language :: Python :: 3.11
Classifier: Programming Language :: Python :: 3.12
Classifier: Topic :: Communications :: Chat
Classifier: Topic :: Software Development :: Libraries :: Python Modules
Classifier: Typing :: Typed
Requires-Python: >=3.8
License-File: LICENSE
Requires-Dist: httpx>=0.25.0
Requires-Dist: pydantic>=2.0.0
Requires-Dist: typing-extensions>=4.5.0
Provides-Extra: dev
Requires-Dist: pytest>=7.4.0; extra == "dev"
Requires-Dist: pytest-asyncio>=0.21.0; extra == "dev"
Requires-Dist: pytest-cov>=4.1.0; extra == "dev"
Requires-Dist: respx>=0.20.0; extra == "dev"
Requires-Dist: black>=23.0.0; extra == "dev"
Requires-Dist: mypy>=1.5.0; extra == "dev"
Requires-Dist: ruff>=0.0.290; extra == "dev"
Dynamic: license-file
